valis_hest/__init__.py
valis_hest/affine_optimizer.py
valis_hest/feature_detectors.py
valis_hest/feature_matcher.py
valis_hest/micro_rigid_registrar.py
valis_hest/non_rigid_registrars.py
valis_hest/preprocessing.py
valis_hest/registration.py
valis_hest/serial_non_rigid.py
valis_hest/serial_rigid.py
valis_hest/slide_io.py
valis_hest/slide_tools.py
valis_hest/valtils.py
valis_hest/viz.py
valis_hest/warp_tools.py
valis_hest-0.0.2.dist-info/METADATA
valis_hest-0.0.2.dist-info/WHEEL
valis_hest-0.0.2.dist-info/top_level.txt
valis_hest-0.0.2.dist-info/RECORD
