Metadata-Version: 2.4
Name: valis_hest
Version: 0.0.2
Summary: Modified version of Valis used for HEST. Please visit the original Valis repo for more information https://github.com/MathOnco/valis
Author-email: Chandler Gatenbee <chandlergatenbee@gmail.com>
Requires-Python: >=3.9
Requires-Dist: beautifulsoup4>=4.11.1
Requires-Dist: scyjava>=1.8.1
Requires-Dist: colorama>=0.4.6
Requires-Dist: colour-science>=0.4.2
Requires-Dist: fastcluster>=1.2.6
Requires-Dist: jpype1>=1.4.1
Requires-Dist: ome-types>=0.5.1.post1
Requires-Dist: opencv-contrib-python>=4.9.0
Requires-Dist: pillow>=9.4.0
Requires-Dist: scipy>=1.10.0
Requires-Dist: scikit-image>=0.19.3
Requires-Dist: simpleitk>=2.2.1
Requires-Dist: weightedstats>=0.4.1
Requires-Dist: aicspylibczi>=3.1.2
Requires-Dist: shapely>=2.0.0
Requires-Dist: tqdm>=4.64.1
Requires-Dist: pqdm>=0.2.0
Requires-Dist: markupsafe>=2.0.0
Requires-Dist: setuptools>=69.0.3
Requires-Dist: lxml>=5.2.2
